hdb_valuation_engine/__init__.py
hdb_valuation_engine/cli.py
hdb_valuation_engine/cli.py.bak
hdb_valuation_engine/cli.py.bak2
hdb_valuation_engine/cli.py.bak3
hdb_valuation_engine/cli.py.bak4
hdb_valuation_engine/fetch.py
hdb_valuation_engine/hdb_valuation_engine.py.old
hdb_valuation_engine/loader.py
hdb_valuation_engine/models.py
hdb_valuation_engine/py.typed
hdb_valuation_engine/reporter.py
hdb_valuation_engine/spatial.py
hdb_valuation_engine/utils.py
hdb_valuation_engine-0.4.0.dist-info/METADATA
hdb_valuation_engine-0.4.0.dist-info/WHEEL
hdb_valuation_engine-0.4.0.dist-info/entry_points.txt
hdb_valuation_engine-0.4.0.dist-info/licenses/LICENSE
hdb_valuation_engine-0.4.0.dist-info/RECORD
