Metadata-Version: 2.4
Name: hdb-valuation-engine
Version: 0.4.0
Summary: Singapore Public Housing (HDB) Valuation Engine using geospatial accessibility scoring.
License: MIT
License-File: LICENSE
Keywords: HDB,Singapore,real-estate,valuation,geospatial,MRT,KDTree,transport,LRT,data-analysis
Author: Mansib "Xenix" Miraj
Requires-Python: >=3.10,<4.0
Classifier: Intended Audience :: Financial and Insurance Industry
Classifier: License :: OSI Approved :: MIT License
Classifier: Operating System :: OS Independent
Classifier: Programming Language :: Python :: 3
Classifier: Programming Language :: Python :: 3.10
Classifier: Programming Language :: Python :: 3.11
Classifier: Programming Language :: Python :: 3.12
Classifier: Programming Language :: Python :: 3.13
Classifier: Programming Language :: Python :: 3.14
Classifier: Topic :: Scientific/Engineering :: GIS
Classifier: Topic :: Scientific/Engineering :: Information Analysis
Requires-Dist: numpy (>=1.26,<2.0)
Requires-Dist: pandas (>=2.1,<3.0)
Requires-Dist: requests (>=2.31,<3.0)
Requires-Dist: scikit-learn (>=1.2,<2.0)
Project-URL: Homepage, https://github.com/theMansib/hdb-valuation-engine
Project-URL: Repository, https://github.com/theMansib/hdb-valuation-engine
